omicron/__init__.py
omicron/_version.py
omicron/condor.py
omicron/const.py
omicron/data.py
omicron/io.py
omicron/log.py
omicron/nagios.py
omicron/parameters.py
omicron/segments.py
omicron/utils.py
omicron/cli/__init__.py
omicron/cli/archive.py
omicron/cli/conda_run.py
omicron/cli/hdf5_merge.py
omicron/cli/merge_with_gaps.py
omicron/cli/omicron_post_script.py
omicron/cli/process.py
omicron/cli/root_merge.py
omicron/cli/show.py
omicron/cli/status.py
omicron/tests/__init__.py
omicron/tests/mock_classad.py
omicron/tests/mock_htcondor.py
omicron/tests/test_condor.py
omicron/tests/test_const.py
omicron/tests/test_io.py
omicron/tests/test_log.py
omicron/tests/test_nagios.py
omicron/tests/test_parameters.py
omicron/tests/test_segments.py
omicron/tests/test_utils.py
omicron/tests/utils.py
pyomicron-2.0.32.dist-info/licenses/LICENSE
pyomicron-2.0.32.dist-info/METADATA
pyomicron-2.0.32.dist-info/WHEEL
pyomicron-2.0.32.dist-info/entry_points.txt
pyomicron-2.0.32.dist-info/top_level.txt
pyomicron-2.0.32.dist-info/RECORD
