Metadata-Version: 2.4
Name: pyomicron
Version: 2.0.32
Summary: Python utilities and wrappers for GW Omicron
Home-page: https://github.com/gwpy/pyomicron
Download-URL: https://pypi.org/project/pyomicron/
Author: Duncan Macleod
Author-email: duncan.macleod@ligo.org
Maintainer: Joseph Areeda
Maintainer-email: joseph.areeda@ligo.org
License: "GPL-3.0-or-later"
Project-URL: Bug Tracker, https://github.com/gwpy/pyomicron/issues
Project-URL: Documentation, https://pyomicron.readthedocs.io
Project-URL: Source Code, https://github.com/gwpy/pyomicron.git
Classifier: Development Status :: 5 - Production/Stable
Classifier: Intended Audience :: Science/Research
Classifier: Intended Audience :: End Users/Desktop
Classifier: Intended Audience :: Developers
Classifier: License :: OSI Approved :: GNU General Public License v3 or later (GPLv3+)
Classifier: Natural Language :: English
Classifier: Operating System :: POSIX
Classifier: Operating System :: Unix
Classifier: Operating System :: MacOS
Classifier: Programming Language :: Python :: 3
Classifier: Programming Language :: Python :: 3.10
Classifier: Programming Language :: Python :: 3.11
Classifier: Topic :: Scientific/Engineering
Classifier: Topic :: Scientific/Engineering :: Astronomy
Classifier: Topic :: Scientific/Engineering :: Physics
Requires-Python: <3.12,>=3.10
License-File: LICENSE
Requires-Dist: dqsegdb2>=1.2.0
Requires-Dist: gpstime
Requires-Dist: gwdatafind
Requires-Dist: gwpy>=2.0.0
Requires-Dist: h5py
Requires-Dist: htcondor
Requires-Dist: igwn-auth-utils[requests]>=0.2.0
Requires-Dist: ligo-segments
Requires-Dist: lscsoft-glue>=1.60.0
Requires-Dist: MarkupPy
Requires-Dist: numpy
Requires-Dist: packaging
Requires-Dist: pycondor
Requires-Dist: python-ligo-lw>=1.4.0
Requires-Dist: omicron_utils
Provides-Extra: test
Requires-Dist: pytest>=3.9.1; extra == "test"
Requires-Dist: pytest-cov; extra == "test"
Requires-Dist: requests-mock; extra == "test"
Provides-Extra: docs
Requires-Dist: numpydoc; extra == "docs"
Requires-Dist: sphinx; extra == "docs"
Requires-Dist: sphinx_rtd_theme; extra == "docs"
Requires-Dist: sphinxcontrib-programoutput; extra == "docs"
Provides-Extra: conda
Requires-Dist: omicron>=2.3.12; extra == "conda"
Dynamic: download-url
Dynamic: license-file
